shared_ndarray2/__init__.py
shared_ndarray2/py.typed
shared_ndarray2/shared_ndarray.py
shared_ndarray2/version.py
shared_ndarray2-2.0.2.dist-info/METADATA
shared_ndarray2-2.0.2.dist-info/WHEEL
shared_ndarray2-2.0.2.dist-info/licenses/LICENSE
shared_ndarray2-2.0.2.dist-info/RECORD
