Metadata-Version: 2.4
Name: shared-ndarray2
Version: 2.0.2
Summary: Interface for NumPy ndarray using multiprocessing SharedMemory
Project-URL: Repository, https://gitlab.com/osu-nrsg/shared-ndarray2
Project-URL: Issues, https://gitlab.com/osu-nrsg/shared-ndarray2/-/issues
Project-URL: Changelog, https://gitlab.com/osu-nrsg/shared-ndarray2/-/blob/master/CHANGELOG.md
Author-email: Randall Pittman <randall.pittman@oregonstate.edu>
License: MIT License
License-File: LICENSE
Keywords: ndarray,numpy,shared_memory
Classifier: Development Status :: 5 - Production/Stable
Classifier: Intended Audience :: Developers
Classifier: License :: OSI Approved :: MIT License
Classifier: Operating System :: OS Independent
Classifier: Programming Language :: Python :: 3.8
Classifier: Programming Language :: Python :: 3.9
Classifier: Programming Language :: Python :: 3.10
Classifier: Programming Language :: Python :: 3.11
Classifier: Programming Language :: Python :: 3.12
Classifier: Programming Language :: Python :: 3.13
Classifier: Topic :: Scientific/Engineering
Classifier: Topic :: Software Development
Requires-Python: >=3.8
Requires-Dist: numpy>=1.21.1
Requires-Dist: packaging>=25.0
Requires-Dist: single-version>=1.5.1
